wsstat/__init__.py
wsstat/clients.py
wsstat/demo.py
wsstat/gui.py
wsstat/main.py
wsstat-1.2.1.dist-info/DESCRIPTION.rst
wsstat-1.2.1.dist-info/METADATA
wsstat-1.2.1.dist-info/RECORD
wsstat-1.2.1.dist-info/WHEEL
wsstat-1.2.1.dist-info/entry_points.txt
wsstat-1.2.1.dist-info/metadata.json
wsstat-1.2.1.dist-info/top_level.txt
